README.txt
setup.py
docs/HISTORY.txt
upfront/__init__.py
upfront.navportlet.egg-info/PKG-INFO
upfront.navportlet.egg-info/SOURCES.txt
upfront.navportlet.egg-info/dependency_links.txt
upfront.navportlet.egg-info/entry_points.txt
upfront.navportlet.egg-info/namespace_packages.txt
upfront.navportlet.egg-info/not-zip-safe
upfront.navportlet.egg-info/requires.txt
upfront.navportlet.egg-info/top_level.txt
upfront/navportlet/__init__.py
upfront/navportlet/configlet.pt
upfront/navportlet/configlet.py
upfront/navportlet/configure.zcml
upfront/navportlet/exportimport.py
upfront/navportlet/interfaces.py
upfront/navportlet/navtool.py
upfront/navportlet/navtree.py
upfront/navportlet/overrides.zcml
upfront/navportlet/portlet.py
upfront/navportlet/tests.py
upfront/navportlet/profiles/default/archetype_tool.xml
upfront/navportlet/profiles/default/catalog.xml
upfront/navportlet/profiles/default/controlpanel.xml
upfront/navportlet/profiles/default/import_steps.xml
upfront/navportlet/profiles/default/toolset.xml