Metadata-Version: 1.0
Name: upfront.navportlet
Version: 1.0
Summary: Navigation porlet with a dedicated catalog
Home-page: http://svn.plone.org/svn/collective/upfront.navportlet
Author: Roche Compaan
Author-email: roche@upfrontsystems.co.za
License: GPL
Keywords: zope plone
Platform: UNKNOWN
Classifier: Programming Language :: Python
Classifier: Framework :: Plone
Classifier: Framework :: Zope2
